<?xml version="1.0" encoding="utf-8"?>
<ReportingModule>
  <Metadata>
    <Label>Alpha angle measurement by MRI</Label>
    <ID>Alpha_angle_measurement_by_MRI</ID>
    <SchemaVersion>2.0</SchemaVersion>
    <ModuleVersion>1.0</ModuleVersion>
    <CreatedDate>2019-11-11</CreatedDate>
    <LastModifiedDate>2019-11-11</LastModifiedDate>
    <DevelopedBy>American College of Radiology</DevelopedBy>
    <CodableConcept Name="codableConcept_Alpha_angle_measurement_by_MRI">
      <Coding>
        <System Value="RadElement" />
        <Version Value="1.0" />
        <Code Value="RDES108" />
        <Display Value="RDES108" />
        <UserSelected Value="false" />
        <Url Value="http://radelement.org/set/RDES108" />
      </Coding>
    </CodableConcept>
    <Info>
      <Description> Alpha angle measurement by MRI</Description>
      <Contact>
        <Name>Jordan Meyer</Name>
        <Institution>American College of Radiology</Institution>
      </Contact>
    </Info>
  </Metadata>
  <DataElements>
    <NumericDataElement Id="alphaangle_0" DisplaySequence="1" Unit="degrees">
      <CodableConcept Name="codableConcept_RDES108_alphaangle_0">
        <Coding>
          <System Value="RadElement" />
          <Version Value="1.0" />
          <Code Value="RDE557" />
          <Display Value="RDE557" />
          <UserSelected Value="false" />
          <Url Value="http://radelement.org/element/RDE557" />
        </Coding>
      </CodableConcept>
      <Label>alpha angle</Label>
      <Hint>alpha angle</Hint>
    </NumericDataElement>
    <ChoiceDataElement Id="sexatbirth_1" DisplaySequence="2">
      <CodableConcept Name="codableConcept_RDES108_sexatbirth_1">
        <Coding>
          <System Value="RadElement" />
          <Version Value="1.0" />
          <Code Value="RDE558" />
          <Display Value="RDE558" />
          <UserSelected Value="false" />
          <Url Value="http://radelement.org/element/RDE558" />
        </Coding>
      </CodableConcept>
      <Label>sex at birth</Label>
      <ChoiceInfo>
        <Choice>
          <Value>male</Value>
          <Label>male</Label>
        </Choice>
        <Choice>
          <Value>female</Value>
          <Label>female</Label>
        </Choice>
      </ChoiceInfo>
    </ChoiceDataElement>
    <IntegerDataElement Id="age_2" IsRequired="true" DisplaySequence="3" Unit="years">
      <CodableConcept Name="codableConcept_RDES108_age_2">
        <Coding>
          <System Value="RadElement" />
          <Version Value="1.0" />
          <Code Value="RDE559" />
          <Display Value="RDE559" />
          <UserSelected Value="false" />
          <Url Value="http://radelement.org/element/RDE559" />
        </Coding>
      </CodableConcept>
      <Label>age</Label>
    </IntegerDataElement>
  </DataElements>
  <Rules />
  <EndPoints />
</ReportingModule>